{
  "global": {
    "rules": {
      "required": "این فیلد الزامیست."
    },
    "templateTitle": "%s | تعالی",
    "option1": "گزینه ۱",
    "option2": "گزینه ۲",
    "option3": "گزینه ۳",
    "option4": "گزینه ۴",
    "hour": "ساعت",
    "sat": "شنبه",
    "sun": "یکشنبه",
    "mon": "دوشنبه",
    "tue": "سه‌شنبه",
    "wed": "چهارشنبه",
    "thu": "پنج‌شنبه",
    "fri": "جمعه",
    "1th": "اول",
    "2th": "دوم",
    "3th": "سوم",
    "4th": "چهارم",
    "5th": "پنجم",
    "6th": "ششم",
    "7th": "هفتم",
    "8th": "هشتم",
    "9th": "نهم",
    "10th": "دهم",
    "11th": "یازدهم",
    "12th": "دوازدهم"
  }
}
